torii_ila/__init__.py
torii_ila/_bits.py
torii_ila/backhaul.py
torii_ila/ila.py
torii_ila/py.typed
torii_ila/uart/__init__.py
torii_ila/uart/_impl.py
torii_ila/usb/__init__.py
torii_ila/usb/_impl.py
torii_ila-0.2.0.dist-info/licenses/LICENSE
torii_ila-0.2.0.dist-info/licenses/LICENSE.docs
torii_ila-0.2.0.dist-info/METADATA
torii_ila-0.2.0.dist-info/WHEEL
torii_ila-0.2.0.dist-info/top_level.txt
torii_ila-0.2.0.dist-info/RECORD
