Metadata-Version: 2.4
Name: torii-ila
Version: 0.2.0
Summary: Integrated Logic Analyzer core for Torii based designs
Author-email: Aki Van Ness <aki@lethalbit.net>
License-Expression: BSD-3-Clause
Project-URL: source, https://github.com/shrine-maiden-heavy-industries/torii-ila
Project-URL: issues, https://github.com/shrine-maiden-heavy-industries/torii-ila/issues
Project-URL: documentation, https://torii-ila.shmdn.link/
Project-URL: changelog, https://torii-ila.shmdn.link/changelog.html
Keywords: Torii,FPGA,ILA,Debugger,Logic Analyzer
Classifier: Development Status :: 4 - Beta
Classifier: Intended Audience :: Developers
Classifier: Intended Audience :: Education
Classifier: Intended Audience :: Information Technology
Classifier: Intended Audience :: Science/Research
Classifier: Operating System :: MacOS :: MacOS X
Classifier: Operating System :: Microsoft :: Windows
Classifier: Operating System :: POSIX :: Linux
Classifier: Programming Language :: Python :: 3.11
Classifier: Programming Language :: Python :: 3.12
Classifier: Programming Language :: Python :: 3.13
Classifier: Programming Language :: Python :: 3.14
Classifier: Programming Language :: Python :: Implementation :: CPython
Classifier: Programming Language :: Python :: Implementation :: PyPy
Classifier: Topic :: Scientific/Engineering
Classifier: Topic :: Scientific/Engineering :: Electronic Design Automation (EDA)
Classifier: Topic :: Software Development
Classifier: Topic :: Software Development :: Embedded Systems
Classifier: Topic :: Software Development :: Libraries
Classifier: Typing :: Typed
Requires-Python: >=3.11
License-File: LICENSE
License-File: LICENSE.docs
Requires-Dist: pyvcd
Requires-Dist: torii<1.0,>=0.8.0
Provides-Extra: dev
Requires-Dist: nox; extra == "dev"
Provides-Extra: usb
Requires-Dist: libusb1>=1.8.1; extra == "usb"
Requires-Dist: pyusb; extra == "usb"
Requires-Dist: torii-usb<1.0,>=0.8.0; extra == "usb"
Provides-Extra: uart
Requires-Dist: pyserial; extra == "uart"
Provides-Extra: examples
Requires-Dist: torii-boards<1.0,>=0.8.1; extra == "examples"
Dynamic: license-file
